Banner_Ad_Toolkit-0.3.2.dist-info/DESCRIPTION.rst
Banner_Ad_Toolkit-0.3.2.dist-info/METADATA
Banner_Ad_Toolkit-0.3.2.dist-info/RECORD
Banner_Ad_Toolkit-0.3.2.dist-info/WHEEL
Banner_Ad_Toolkit-0.3.2.dist-info/entry_points.txt
Banner_Ad_Toolkit-0.3.2.dist-info/metadata.json
Banner_Ad_Toolkit-0.3.2.dist-info/top_level.txt
adkit/__init__.py
adkit/adkit.py
adkit/create_zips.py
adkit/generate_css.py
adkit/generate_html.py
adkit/generate_js.py
adkit/optimize_images.py
adkit/quickstart.py
adkit/upload_html.py
adkit/templates/.DS_Store
adkit/templates/__init__.pyc
adkit/templates/style.css
adkit/templates/adwords/index.html
adkit/templates/adwords/script.js
adkit/templates/dcm/index.html
adkit/templates/dcm/script.js
adkit/templates/doubleclick/index.html
adkit/templates/doubleclick/script.js
adkit/templates/quickstart/.DS_Store
adkit/templates/quickstart/adkit.ini
adkit/templates/sizemek/index.html
adkit/templates/sizemek/script.js
