Metadata-Version: 2.0
Name: Banner-Ad-Toolkit
Version: 0.3.2
Summary: A command line tool to aid in the development of banner ad campaigns. Auto generates PSDs at the required sizes with specified filenames to get you started, then when done designing, exports static banners at or under max file sizes specified. All managed via a very simple manifest file.
Home-page: https://bitbucket.org/tsantor/banner-ad-toolkit
Author: Tim Santor
Author-email: tsantor@xstudios.agency
License: MIT
Download-URL: https://bitbucket.org/tsantor/banner-ad-toolkit/get/0.3.2.tar.gz
Keywords: banner ad
Platform: UNKNOWN
Classifier: Development Status :: 3 - Alpha
Classifier: Environment :: Console
Classifier: Intended Audience :: Developers
Classifier: Topic :: Software Development :: Build Tools
Classifier: License :: OSI Approved :: MIT License
Classifier: Programming Language :: Python :: 2.7
Classifier: Programming Language :: Python :: 3.4
Requires-Dist: cssutils (>=1.0.2,<2)
Requires-Dist: pillow (<5,>=4.1.1)
Requires-Dist: progressbar33 (>=2.4,<3)
Requires-Dist: python-bash-utils (>=0.1.2)
